LICENSE
MANIFEST.in
README.md
setup.py
pyfant/__init__.py
pyfant/_star.py
pyfant/from_turbospectrum.py
pyfant/from_vald.py
pyfant/kovacs.py
pyfant/molconsts.py
pyfant/util.py
pyfant.egg-info/PKG-INFO
pyfant.egg-info/SOURCES.txt
pyfant.egg-info/dependency_links.txt
pyfant.egg-info/requires.txt
pyfant.egg-info/top_level.txt
pyfant/basic/__init__.py
pyfant/basic/constants.py
pyfant/basic/conversion.py
pyfant/basic/errors.py
pyfant/basic/misc.py
pyfant/basic/paths.py
pyfant/convmol/__init__.py
pyfant/convmol/calc_qgbd.py
pyfant/convmol/conv.py
pyfant/convmol/conv_brooke2014.py
pyfant/convmol/conv_hitran.py
pyfant/convmol/conv_hitran160.py
pyfant/convmol/conv_kurucz.py
pyfant/convmol/conv_plez.py
pyfant/convmol/conv_vald3.py
pyfant/convmol/convlog.py
pyfant/data/default/abonds.dat
pyfant/data/default/absoru2.dat
pyfant/data/default/abxfwhm.py
pyfant/data/default/configconvmol.py
pyfant/data/default/configmolconsts.py
pyfant/data/default/dissoc.dat
pyfant/data/default/hitrandb.sqlite
pyfant/data/default/hmap.dat
pyfant/data/default/main.dat
pyfant/data/default/modeles.mod
pyfant/data/default/moldb.sqlite
pyfant/data/default/partit.dat
pyfant/downloaders/__init__.py
pyfant/downloaders/downhitran.py
pyfant/downloaders/downnist.py
pyfant/filetypes/__init__.py
pyfant/filetypes/fileabonds.py
pyfant/filetypes/fileabsoru2.py
pyfant/filetypes/fileabxfwhm.py
pyfant/filetypes/fileatoms.py
pyfant/filetypes/filebrooke2014.py
pyfant/filetypes/filecojm1998.py
pyfant/filetypes/fileconfconvmol.py
pyfant/filetypes/filedissoc.py
pyfant/filetypes/filehitran160.py
pyfant/filetypes/filehitrandb.py
pyfant/filetypes/filehmap.py
pyfant/filetypes/filekuruczmol.py
pyfant/filetypes/filemain.py
pyfant/filetypes/filemod.py
pyfant/filetypes/filemolconsts.py
pyfant/filetypes/filemoldb.py
pyfant/filetypes/filemolecules.py
pyfant/filetypes/filemollist.py
pyfant/filetypes/fileoptions.py
pyfant/filetypes/filepartit.py
pyfant/filetypes/fileplezlinelist.py
pyfant/filetypes/filepleztio.py
pyfant/filetypes/filetoh.py
pyfant/filetypes/filetraprb.py
pyfant/filetypes/filevald3.py
pyfant/filetypes/morespectra.py
pyfant/gui/__init__.py
pyfant/gui/_shared.py
