Metadata-Version: 2.1
Name: pyfant
Version: 24.9.2.1
Summary: Python interface to the PFANT spectral synthesis code, with a varied set of extra tools
Home-page: https://github.com/trevisanj/pyfant
Author: Julio Trevisan
Author-email: juliotrevisan@gmail.com
License: GNU GPLv3
Keywords: astronomy,stellar,spectroscopy,spectral,synthesis,honl-london,nist,hitran,multiplicity,line strength,kovacs,franck-condon
Platform: any
License-File: LICENSE
